ruprof-0.1.1.dist-info/METADATA
ruprof-0.1.1.dist-info/WHEEL
ruprof/__init__.py
ruprof/ruprof.cpython-38-x86_64-linux-gnu.so
ruprof-0.1.1.dist-info/RECORD
