Metadata-Version: 2.4
Name: ruprof
Version: 0.1.1
Classifier: Programming Language :: Rust
Classifier: Programming Language :: Python :: Implementation :: CPython
Classifier: Programming Language :: Python :: Implementation :: PyPy
Requires-Dist: libcst>=1.1.0
Requires-Python: >=3.8
